[{"DLC":false,"EXPANSION":0,"ID":1,"MAX_LEVEL":2,"MIN_LEVEL":1,"NAME":"AMMO:300G_ARROW","PENETRATION":10,"PRICE":530,"RANGE_M":20,"RANGE_YD":21.87,"SCORE":700},{"DLC":false,"EXPANSION":0,"ID":2,"MAX_LEVEL":7,"MIN_LEVEL":2,"NAME":"AMMO:420G_ARROW","PENETRATION":50,"PRICE":700,"RANGE_M":20,"RANGE_YD":21.87,"SCORE":0},{"DLC":false,"EXPANSION":0,"ID":3,"MAX_LEVEL":9,"MIN_LEVEL":7,"NAME":"AMMO:600G_ARROW","PENETRATION":90,"PRICE":880,"RANGE_M":20,"RANGE_YD":21.87,"SCORE":3500},{"DLC":true,"EXPANSION":0,"ID":4,"MAX_LEVEL":3,"MIN_LEVEL":1,"NAME":"AMMO:350G_ARROW","PENETRATION":15,"PRICE":500,"RANGE_M":20,"RANGE_YD":21.87,"SCORE":0},{"DLC":true,"EXPANSION":0,"ID":5,"MAX_LEVEL":7,"MIN_LEVEL":4,"NAME":"AMMO:540G_ARROW","PENETRATION":75,"PRICE":750,"RANGE_M":20,"RANGE_YD":21.87,"SCORE":0},{"DLC":true,"EXPANSION":0,"ID":6,"MAX_LEVEL":9,"MIN_LEVEL":8,"NAME":"AMMO:700G_ARROW","PENETRATION":90,"PRICE":900,"RANGE_M":20,"RANGE_YD":21.87,"SCORE":0},{"DLC":true,"EXPANSION":0,"ID":7,"MAX_LEVEL":1,"MIN_LEVEL":1,"NAME":"AMMO:410_BIRDSHOT","PENETRATION":0,"PRICE":200,"RANGE_M":25,"RANGE_YD":27.34,"SCORE":0},{"DLC":false,"EXPANSION":12,"ID":8,"MAX_LEVEL":4,"MIN_LEVEL":2,"NAME":"AMMO:223_SOFT","PENETRATION":10,"PRICE":220,"RANGE_M":150,"RANGE_YD":164.04,"SCORE":0},{"DLC":false,"EXPANSION":3,"ID":9,"MAX_LEVEL":4,"MIN_LEVEL":2,"NAME":"AMMO:223_POLYMER","PENETRATION":20,"PRICE":350,"RANGE_M":150,"RANGE_YD":164.04,"SCORE":0},{"DLC":false,"EXPANSION":17,"ID":10,"MAX_LEVEL":6,"MIN_LEVEL":2,"NAME":"AMMO:243_SOFT","PENETRATION":15,"PRICE":0,"RANGE_M":150,"RANGE_YD":164.04,"SCORE":0},{"DLC":false,"EXPANSION":4,"ID":11,"MAX_LEVEL":6,"MIN_LEVEL":2,"NAME":"AMMO:243_POLYMER","PENETRATION":30,"PRICE":530,"RANGE_M":150,"RANGE_YD":164.04,"SCORE":50},{"DLC":false,"EXPANSION":24,"ID":12,"MAX_LEVEL":8,"MIN_LEVEL":4,"NAME":"AMMO:270_SOFT","PENETRATION":17,"PRICE":440,"RANGE_M":150,"RANGE_YD":164.04,"SCORE":0},{"DLC":false,"EXPANSION":5,"ID":13,"MAX_LEVEL":8,"MIN_LEVEL":4,"NAME":"AMMO:270_POLYMER","PENETRATION":35,"PRICE":700,"RANGE_M":150,"RANGE_YD":164.04,"SCORE":700},{"DLC":false,"EXPANSION":53,"ID":14,"MAX_LEVEL":9,"MIN_LEVEL":4,"NAME":"AMMO:7MM_SOFT","PENETRATION":20,"PRICE":610,"RANGE_M":150,"RANGE_YD":164.04,"SCORE":0},{"DLC":false,"EXPANSION":12,"ID":15,"MAX_LEVEL":9,"MIN_LEVEL":4,"NAME":"AMMO:7MM_POLYMER","PENETRATION":40,"PRICE":880,"RANGE_M":150,"RANGE_YD":164.04,"SCORE":0},{"DLC":true,"EXPANSION":60,"ID":16,"MAX_LEVEL":9,"MIN_LEVEL":7,"NAME":"AMMO:300_SOFT","PENETRATION":21,"PRICE":720,"RANGE_M":150,"RANGE_YD":164.04,"SCORE":6000},{"DLC":true,"EXPANSION":14,"ID":17,"MAX_LEVEL":9,"MIN_LEVEL":7,"NAME":"AMMO:300_POLYMER","PENETRATION":42,"PRICE":950,"RANGE_M":150,"RANGE_YD":164.04,"SCORE":6400},{"DLC":false,"EXPANSION":27,"ID":18,"MAX_LEVEL":9,"MIN_LEVEL":4,"NAME":"AMMO:4570_HOLLOW","PENETRATION":20,"PRICE":660,"RANGE_M":75,"RANGE_YD":82.02,"SCORE":2800},{"DLC":false,"EXPANSION":6,"ID":19,"MAX_LEVEL":9,"MIN_LEVEL":4,"NAME":"AMMO:4570_SOFT","PENETRATION":40,"PRICE":390,"RANGE_M":75,"RANGE_YD":82.02,"SCORE":3500},{"DLC":true,"EXPANSION":53,"ID":20,"MAX_LEVEL":8,"MIN_LEVEL":4,"NAME":"AMMO:303_SOFT","PENETRATION":20,"PRICE":610,"RANGE_M":150,"RANGE_YD":164.04,"SCORE":0},{"DLC":true,"EXPANSION":12,"ID":21,"MAX_LEVEL":8,"MIN_LEVEL":4,"NAME":"AMMO:303_POLYMER","PENETRATION":40,"PRICE":880,"RANGE_M":150,"RANGE_YD":164.04,"SCORE":0},{"DLC":true,"EXPANSION":100,"ID":22,"MAX_LEVEL":9,"MIN_LEVEL":9,"NAME":"AMMO:470_SOFT","PENETRATION":25,"PRICE":2000,"RANGE_M":75,"RANGE_YD":82.02,"SCORE":5700},{"DLC":true,"EXPANSION":23,"ID":23,"MAX_LEVEL":9,"MIN_LEVEL":9,"NAME":"AMMO:470_FULL_METAL_JACKET","PENETRATION":100,"PRICE":2660,"RANGE_M":75,"RANGE_YD":82.02,"SCORE":6500},{"DLC":true,"EXPANSION":20,"ID":24,"MAX_LEVEL":8,"MIN_LEVEL":4,"NAME":"AMMO:65MM_SOFT","PENETRATION":20,"PRICE":400,"RANGE_M":200,"RANGE_YD":218.72,"SCORE":350},{"DLC":true,"EXPANSION":4,"ID":25,"MAX_LEVEL":8,"MIN_LEVEL":4,"NAME":"AMMO:65MM_POLYMER","PENETRATION":40,"PRICE":650,"RANGE_M":200,"RANGE_YD":218.72,"SCORE":550},{"DLC":false,"EXPANSION":68,"ID":26,"MAX_LEVEL":9,"MIN_LEVEL":7,"NAME":"AMMO:338_SOFT","PENETRATION":22,"PRICE":790,"RANGE_M":150,"RANGE_YD":164.04,"SCORE":0},{"DLC":false,"EXPANSION":16,"ID":27,"MAX_LEVEL":9,"MIN_LEVEL":7,"NAME":"AMMO:338_POLYMER","PENETRATION":45,"PRICE":1050,"RANGE_M":150,"RANGE_YD":164.04,"SCORE":0},{"DLC":true,"EXPANSION":17,"ID":28,"MAX_LEVEL":7,"MIN_LEVEL":3,"NAME":"AMMO:762X54R_SOFT","PENETRATION":15,"PRICE":380,"RANGE_M":150,"RANGE_YD":164.04,"SCORE":0},{"DLC":true,"EXPANSION":10,"ID":29,"MAX_LEVEL":1,"MIN_LEVEL":1,"NAME":"AMMO:22LR_HOLLOW","PENETRATION":5,"PRICE":200,"RANGE_M":100,"RANGE_YD":109.36,"SCORE":0},{"DLC":false,"EXPANSION":17,"ID":30,"MAX_LEVEL":6,"MIN_LEVEL":2,"NAME":"AMMO:3030_HOLLOW","PENETRATION":17,"PRICE":480,"RANGE_M":75,"RANGE_YD":82.02,"SCORE":1000},{"DLC":false,"EXPANSION":4,"ID":31,"MAX_LEVEL":6,"MIN_LEVEL":2,"NAME":"AMMO:3030_SOFT","PENETRATION":35,"PRICE":220,"RANGE_M":75,"RANGE_YD":82.02,"SCORE":1300},{"DLC":false,"EXPANSION":70,"ID":32,"MAX_LEVEL":8,"MIN_LEVEL":3,"NAME":"AMMO:44_HOLLOW","PENETRATION":17,"PRICE":260,"RANGE_M":50,"RANGE_YD":54.68,"SCORE":0},{"DLC":false,"EXPANSION":16,"ID":33,"MAX_LEVEL":8,"MIN_LEVEL":3,"NAME":"AMMO:44_FLAT","PENETRATION":70,"PRICE":530,"RANGE_M":50,"RANGE_YD":54.68,"SCORE":2500},{"DLC":false,"EXPANSION":18,"ID":34,"MAX_LEVEL":6,"MIN_LEVEL":2,"NAME":"AMMO:357_HOLLOW","PENETRATION":12,"PRICE":220,"RANGE_M":50,"RANGE_YD":54.68,"SCORE":0},{"DLC":false,"EXPANSION":4,"ID":35,"MAX_LEVEL":6,"MIN_LEVEL":2,"NAME":"AMMO:357_FLAT","PENETRATION":50,"PRICE":350,"RANGE_M":50,"RANGE_YD":54.68,"SCORE":450},{"DLC":true,"EXPANSION":70,"ID":36,"MAX_LEVEL":5,"MIN_LEVEL":2,"NAME":"AMMO:45_FLAT","PENETRATION":17,"PRICE":530,"RANGE_M":50,"RANGE_YD":54.68,"SCORE":0},{"DLC":false,"EXPANSION":100,"ID":37,"MAX_LEVEL":9,"MIN_LEVEL":4,"NAME":"AMMO:454_HOLLOW","PENETRATION":25,"PRICE":440,"RANGE_M":50,"RANGE_YD":54.68,"SCORE":0},{"DLC":false,"EXPANSION":23,"ID":38,"MAX_LEVEL":9,"MIN_LEVEL":4,"NAME":"AMMO:454_FLAT","PENETRATION":100,"PRICE":770,"RANGE_M":50,"RANGE_YD":54.68,"SCORE":5300},{"DLC":true,"EXPANSION":70,"ID":39,"MAX_LEVEL":4,"MIN_LEVEL":2,"NAME":"AMMO:45_HOLLOW","PENETRATION":15,"PRICE":200,"RANGE_M":50,"RANGE_YD":54.68,"SCORE":0},{"DLC":true,"EXPANSION":6,"ID":40,"MAX_LEVEL":4,"MIN_LEVEL":2,"NAME":"AMMO:45_SOFT","PENETRATION":27,"PRICE":300,"RANGE_M":50,"RANGE_YD":54.68,"SCORE":0},{"DLC":true,"EXPANSION":53,"ID":41,"MAX_LEVEL":8,"MIN_LEVEL":4,"NAME":"AMMO:3006_SOFT","PENETRATION":19,"PRICE":590,"RANGE_M":150,"RANGE_YD":164.04,"SCORE":0},{"DLC":true,"EXPANSION":13,"ID":42,"MAX_LEVEL":8,"MIN_LEVEL":4,"NAME":"AMMO:3006_POLYMER","PENETRATION":45,"PRICE":850,"RANGE_M":150,"RANGE_YD":164.04,"SCORE":0},{"DLC":true,"EXPANSION":30,"ID":43,"MAX_LEVEL":7,"MIN_LEVEL":3,"NAME":"AMMO:50_ROUND","PENETRATION":30,"PRICE":300,"RANGE_M":100,"RANGE_YD":109.36,"SCORE":0},{"DLC":true,"EXPANSION":30,"ID":44,"MAX_LEVEL":8,"MIN_LEVEL":4,"NAME":"AMMO:50_MINIE","PENETRATION":40,"PRICE":450,"RANGE_M":200,"RANGE_YD":218.72,"SCORE":0},{"DLC":true,"EXPANSION":53,"ID":45,"MAX_LEVEL":9,"MIN_LEVEL":5,"NAME":"AMMO:93X74R_SOFT","PENETRATION":20,"PRICE":610,"RANGE_M":150,"RANGE_YD":164.04,"SCORE":0},{"DLC":true,"EXPANSION":12,"ID":46,"MAX_LEVEL":9,"MIN_LEVEL":5,"NAME":"AMMO:93X74R_POLYMER","PENETRATION":40,"PRICE":880,"RANGE_M":150,"RANGE_YD":164.04,"SCORE":0},{"DLC":true,"EXPANSION":0,"ID":47,"MAX_LEVEL":1,"MIN_LEVEL":1,"NAME":"AMMO:16GA_BIRDSHOT","PENETRATION":0,"PRICE":180,"RANGE_M":25,"RANGE_YD":27.34,"SCORE":0},{"DLC":true,"EXPANSION":0,"ID":48,"MAX_LEVEL":4,"MIN_LEVEL":2,"NAME":"AMMO:16GA_BUCKSHOT","PENETRATION":5,"PRICE":530,"RANGE_M":25,"RANGE_YD":27.34,"SCORE":0},{"DLC":true,"EXPANSION":16,"ID":49,"MAX_LEVEL":7,"MIN_LEVEL":4,"NAME":"AMMO:16GA_SLUG","PENETRATION":37,"PRICE":880,"RANGE_M":50,"RANGE_YD":54.68,"SCORE":0},{"DLC":false,"EXPANSION":0,"ID":50,"MAX_LEVEL":1,"MIN_LEVEL":1,"NAME":"AMMO:12GA_BIRDSHOT","PENETRATION":0,"PRICE":180,"RANGE_M":25,"RANGE_YD":27.34,"SCORE":150},{"DLC":false,"EXPANSION":0,"ID":51,"MAX_LEVEL":5,"MIN_LEVEL":2,"NAME":"AMMO:12GA_BUCKSHOT","PENETRATION":5,"PRICE":530,"RANGE_M":25,"RANGE_YD":27.34,"SCORE":0},{"DLC":false,"EXPANSION":19,"ID":52,"MAX_LEVEL":8,"MIN_LEVEL":4,"NAME":"AMMO:12GA_SLUG","PENETRATION":40,"PRICE":880,"RANGE_M":50,"RANGE_YD":54.68,"SCORE":3100},{"DLC":true,"EXPANSION":0,"ID":53,"MAX_LEVEL":1,"MIN_LEVEL":1,"NAME":"AMMO:20GA_STEEL_BIRDSHOT","PENETRATION":0,"PRICE":150,"RANGE_M":25,"RANGE_YD":27.34,"SCORE":0},{"DLC":true,"EXPANSION":0,"ID":54,"MAX_LEVEL":1,"MIN_LEVEL":1,"NAME":"AMMO:20GA_BIRDSHOT","PENETRATION":0,"PRICE":150,"RANGE_M":25,"RANGE_YD":27.34,"SCORE":0},{"DLC":true,"EXPANSION":0,"ID":55,"MAX_LEVEL":3,"MIN_LEVEL":2,"NAME":"AMMO:20GA_BUCKSHOT","PENETRATION":4,"PRICE":500,"RANGE_M":25,"RANGE_YD":27.34,"SCORE":0},{"DLC":true,"EXPANSION":16,"ID":56,"MAX_LEVEL":7,"MIN_LEVEL":4,"NAME":"AMMO:20GA_SLUG","PENETRATION":33,"PRICE":800,"RANGE_M":50,"RANGE_YD":54.68,"SCORE":0},{"DLC":true,"EXPANSION":0,"ID":57,"MAX_LEVEL":1,"MIN_LEVEL":1,"NAME":"AMMO:10GA_BIRDSHOT","PENETRATION":0,"PRICE":200,"RANGE_M":25,"RANGE_YD":27.34,"SCORE":0},{"DLC":true,"EXPANSION":0,"ID":58,"MAX_LEVEL":7,"MIN_LEVEL":4,"NAME":"AMMO:10GA_BUCKSHOT","PENETRATION":5,"PRICE":600,"RANGE_M":25,"RANGE_YD":27.34,"SCORE":0},{"DLC":true,"EXPANSION":22,"ID":59,"MAX_LEVEL":9,"MIN_LEVEL":6,"NAME":"AMMO:10GA_SLUG","PENETRATION":45,"PRICE":950,"RANGE_M":50,"RANGE_YD":54.68,"SCORE":0},{"DLC":true,"EXPANSION":0,"ID":60,"MAX_LEVEL":2,"MIN_LEVEL":1,"NAME":"AMMO:300G_BOLT","PENETRATION":10,"PRICE":600,"RANGE_M":30,"RANGE_YD":32.81,"SCORE":0},{"DLC":true,"EXPANSION":0,"ID":61,"MAX_LEVEL":7,"MIN_LEVEL":2,"NAME":"AMMO:420G_BOLT","PENETRATION":50,"PRICE":770,"RANGE_M":30,"RANGE_YD":32.81,"SCORE":0},{"DLC":true,"EXPANSION":0,"ID":62,"MAX_LEVEL":9,"MIN_LEVEL":7,"NAME":"AMMO:600G_BOLT","PENETRATION":90,"PRICE":950,"RANGE_M":30,"RANGE_YD":32.81,"SCORE":0},{"DLC":true,"EXPANSION":3,"ID":63,"MAX_LEVEL":2,"MIN_LEVEL":1,"NAME":"AMMO:22H_POLYMER","PENETRATION":15,"PRICE":300,"RANGE_M":150,"RANGE_YD":164.04,"SCORE":0},{"DLC":true,"EXPANSION":10,"ID":64,"MAX_LEVEL":2,"MIN_LEVEL":1,"NAME":"AMMO:22H_SOFT","PENETRATION":7,"PRICE":200,"RANGE_M":150,"RANGE_YD":164.04,"SCORE":0},{"DLC":true,"EXPANSION":52,"ID":65,"MAX_LEVEL":8,"MIN_LEVEL":4,"NAME":"AMMO:308_SOFT","PENETRATION":19,"PRICE":690,"RANGE_M":150,"RANGE_YD":164.04,"SCORE":0},{"DLC":true,"EXPANSION":13,"ID":66,"MAX_LEVEL":8,"MIN_LEVEL":4,"NAME":"AMMO:308_POLYMER","PENETRATION":44,"PRICE":850,"RANGE_M":150,"RANGE_YD":164.04,"SCORE":0},{"DLC":true,"EXPANSION":1,"ID":67,"MAX_LEVEL":1,"MIN_LEVEL":1,"NAME":"AMMO:22LR_TRUNCATED_CONE","PENETRATION":17,"PRICE":250,"RANGE_M":100,"RANGE_YD":109.36,"SCORE":0},{"DLC":true,"EXPANSION":6,"ID":68,"MAX_LEVEL":5,"MIN_LEVEL":2,"NAME":"AMMO:45_FULL_METAL_JACKET","PENETRATION":55,"PRICE":600,"RANGE_M":50,"RANGE_YD":54.68,"SCORE":0},{"DLC":true,"EXPANSION":8,"ID":69,"MAX_LEVEL":6,"MIN_LEVEL":2,"NAME":"AMMO:10MM_FLAT","PENETRATION":50,"PRICE":350,"RANGE_M":50,"RANGE_YD":54.68,"SCORE":0},{"DLC":true,"EXPANSION":36,"ID":70,"MAX_LEVEL":6,"MIN_LEVEL":2,"NAME":"AMMO:10MM_HOLLOW","PENETRATION":12,"PRICE":280,"RANGE_M":50,"RANGE_YD":54.68,"SCORE":0},{"DLC":true,"EXPANSION":20,"ID":71,"MAX_LEVEL":8,"MIN_LEVEL":4,"NAME":"AMMO:50_POLYMER","PENETRATION":42,"PRICE":500,"RANGE_M":200,"RANGE_YD":218.72,"SCORE":0},{"DLC":true,"EXPANSION":60,"ID":72,"MAX_LEVEL":8,"MIN_LEVEL":4,"NAME":"AMMO:50_HOLLOW","PENETRATION":20,"PRICE":450,"RANGE_M":200,"RANGE_YD":218.72,"SCORE":0},{"DLC":true,"EXPANSION":15,"ID":73,"MAX_LEVEL":4,"MIN_LEVEL":2,"NAME":"AMMO:22250_SOFT","PENETRATION":12,"PRICE":230,"RANGE_M":150,"RANGE_YD":164.04,"SCORE":0},{"DLC":true,"EXPANSION":3,"ID":74,"MAX_LEVEL":4,"MIN_LEVEL":2,"NAME":"AMMO:22250_POLYMER","PENETRATION":25,"PRICE":375,"RANGE_M":150,"RANGE_YD":164.04,"SCORE":0},{"DLC":true,"EXPANSION":60,"ID":75,"MAX_LEVEL":8,"MIN_LEVEL":4,"NAME":"AMMO:577450_BLACK_POWDER","PENETRATION":53,"PRICE":230,"RANGE_M":200,"RANGE_YD":218.72,"SCORE":0}]